[
  {
    "id": "unex-ugv",
    "name": "UNEX UGV",
    "manufacturer": "Ukrainian (domestic)",
    "codified": "2025-04",
    "category": "amphibious_platform",
    "weight_class": "medium",
    "type": "UGV",
    "specs": {
      "mobility": {
        "terrain": ["water", "floodplains", "swamps", "mire", "sand", "ice", "difficult_surfaces"],
        "ground_pressure": "less_than_infantry_soldier_foot",
        "features": ["amphibious", "wide_tires", "specialized_chassis"]
      },
      "propulsion": {
        "type": "electric",
        "battery": "high_capacity"
      },
      "protection": {
        "mine_resistance": "high_pressure_distribution_prevents_activation",
        "armor": "armored_platform"
      },
      "control": {
        "type": "radio_controlled",
        "ew_resistance": "high",
        "autonomy": "programmable_autopilot"
      },
      "configurations": [
        "weapon_station",
        "electronic_warfare",
        "logistics",
        "evacuation",
        "demining"
      ]
    },
    "status": "operational",
    "source": "Ministry of Defence Ukraine"
  },
  {
    "id": "protector-ugv",
    "name": "PROTECTOR",
    "manufacturer": "Ukrainian Armor (domestic)",
    "codified": "2025-08",
    "category": "heavy_logistics_combat",
    "weight_class": "heavy",
    "type": "UGV",
    "specs": {
      "payload_capacity_kg": 700,
      "operational_range_km": 400,
      "propulsion": {
        "type": "internal_combustion",
        "fuel": "diesel_gasoline"
      },
      "mobility": {
        "drive": "all_wheel_drive",
        "tires": "runflat",
        "terrain": ["off_road", "water_crossings", "steep_obstacles"],
        "features": ["excellent_off_road", "overcomes_significant_obstacles"]
      },
      "configurations": [
        "ammunition_transport",
        "casualty_evacuation",
        "weapon_station_platform",
        "mobile_ew",
        "sigint",
        "elint"
      ]
    },
    "status": "operational",
    "source": "Ministry of Defence Ukraine"
  },
  {
    "id": "dodger-ugv",
    "name": "DODGER",
    "manufacturer": "Ukrainian (combat_informed_development)",
    "codified": "2025-06",
    "category": "multi_functional_compact",
    "weight_class": "light_medium",
    "type": "UGV",
    "specs": {
      "payload_capacity_kg": 250,
      "dimensions": "compact_low_profile",
      "protection": {
        "armor": "protective_plating",
        "resistance": ["small_arms_fire", "shrapnel"]
      },
      "missions": [
        "logistics_transport",
        "casualty_evacuation",
        "mine_deployment",
        "combat_engineering"
      ]
    },
    "status": "operational",
    "source": "Ministry of Defence Ukraine"
  },
  {
    "id": "termit-ugv",
    "name": "TERMIT",
    "manufacturer": "Tencore (Ukrainian)",
    "codified": "2025-06",
    "category": "modular_all_terrain",
    "weight_class": "medium",
    "type": "UGV",
    "specs": {
      "payload_capacity_kg": 300,
      "chassis": "tracked",
      "center_of_gravity": "low",
      "terrain": ["rough_ground", "steep_slopes", "trenches", "obstacles"],
      "propulsion": {
        "type": "battery",
        "endurance": "several_continuous_hours",
        "range": "tens_of_kilometers"
      },
      "features": ["modular", "improved_dynamic_performance"],
      "configurations": [
        "medical_evacuation",
        "supply_transport",
        "route_clearance",
        "mining",
        "combat_modules"
      ],
      "production": {
        "planned_units": 2000,
        "investment_usd": 3740000
      }
    },
    "status": "operational_mass_production_planned",
    "source": "Ministry of Defence Ukraine, Tencore"
  },
  {
    "id": "krampus-strike",
    "name": "KRAMPUS",
    "manufacturer": "Ukrainian (domestic)",
    "codified": "2025",
    "category": "mobile_strike_thermobaric",
    "weight_class": "compact",
    "type": "UGV",
    "specs": {
      "transport": ["pickup_truck", "minibus", "trailer"],
      "propulsion": {
        "type": "electric",
        "motors": "dual_silent_electric",
        "chassis": "tracked",
        "battery": "extended_duty_hours"
      },
      "mobility": {
        "terrain": ["off_road", "dense_forests", "sand", "swamps", "steep_slopes"]
      },
      "control": {
        "ew_resistance": "high",
        "weather": ["cold", "heat", "snow", "rain"]
      },
      "payload": {
        "weapon": "RPV-16_reactive_thermobaric_launchers",
        "quantity": 2,
        "targets": ["enemy_personnel", "lightly_armored_vehicles"]
      },
      "sensors": ["video_cameras"]
    },
    "status": "operational",
    "source": "Ministry of Defence Ukraine"
  },
  {
    "id": "droid-tw",
    "name": "Droid TW",
    "manufacturer": "devdroid.tech (Ukrainian)",
    "codified": "2024-12",
    "category": "ai_combat_reconnaissance",
    "weight_class": "medium",
    "type": "UGV",
    "specs": {
      "ai_capabilities": {
        "enemy_recognition": true,
        "target_tracking": true,
        "autonomous_detection": true
      },
      "weapons": [
        {
          "caliber_mm": 12.7,
          "type": "Browning_machine_gun"
        },
        {
          "caliber_mm": 7.62,
          "type": "machine_gun"
        }
      ],
      "ammunition_capacity": [480, 1000],
      "effective_range_m": 1000,
      "detection": {
        "day_range_m": 1500,
        "night_range_m": 1000,
        "thermal_imager": true,
        "display_modes": "multiple"
      },
      "computing": {
        "ballistic_calculation": true
      },
      "communication": ["military_systems", "Starlink", "LTE"],
      "deployment_time_minutes": 5,
      "control": ["tablet", "gamepad"]
    },
    "status": "operational",
    "source": "Ministry of Defence Ukraine"
  },
  {
    "id": "bufalo-ugv",
    "name": "Bufalo",
    "manufacturer": "Ukrainian (undisclosed)",
    "codified": "testing_2025",
    "category": "heavy_ai_diesel",
    "weight_class": "heavy",
    "type": "UGV",
    "specs": {
      "weight_kg": 4000,
      "speed_kmh": 20,
      "profile": "low_difficult_to_detect",
      "propulsion": {
        "type": "diesel",
        "fuel_tanks": "configurable",
        "range_km": [100, 200]
      },
      "ai_capabilities": {
        "local_navigation": true,
        "obstacle_detection_range_m": 15,
        "route_planning": true,
        "danger_response": "autonomous_stop"
      },
      "protection": {
        "armor": "resists_small_arms_fire",
        "blast_resistance": "152mm_shells_within_100m"
      },
      "communication": {
        "primary": "Starlink",
        "secondary": "radio_channel",
        "gps": "crpa_antenna_ew_protected"
      },
      "local_content_percent": 70,
      "components": {
        "domestic": ["electronics", "cameras"],
        "imported": "basic_components_from_EU"
      },
      "production_planned_monthly": 10,
      "roles": [
        "logistics",
        "humanitarian_demining",
        "combat_module_being_consulted",
        "engineering_vehicle_trench_digging"
      ]
    },
    "status": "testing_pre_production",
    "source": "Oboronka, Ukrainska Pravda"
  }
]